poium/__init__.py
poium/base_page.py
poium/common/__init__.py
poium/common/exceptions.py
poium/common/keyboard.py
poium/common/logging.py
poium/common/openatx.py
poium/common/selector.py
poium/config.py
poium/javascript.py
poium/libs/__init__.py
poium/libs/func_timeout.py
poium/playwright.py
poium/u2/__init__.py
poium/u2/driver.py
poium/wda/__init__.py
poium/wda/driver.py
poium/webdriver.py
poium-1.6.4.dist-info/LICENSE
poium-1.6.4.dist-info/METADATA
poium-1.6.4.dist-info/WHEEL
poium-1.6.4.dist-info/RECORD
