Metadata-Version: 2.1
Name: poium
Version: 1.6.4
Summary: Page Objects design pattern test library.
Home-page: https://seldomqa.github.io
License: Apache-2.0
Keywords: selenium,appium,playwright
Author: fnngj
Author-email: fnngj@126.com
Requires-Python: >=3.8
Classifier: Intended Audience :: Developers
Classifier: License :: OSI Approved :: Apache Software License
Classifier: Operating System :: MacOS :: MacOS X
Classifier: Operating System :: Microsoft :: Windows
Classifier: Programming Language :: Python :: 3
Classifier: Programming Language :: Python :: 3.8
Classifier: Programming Language :: Python :: 3.9
Classifier: Programming Language :: Python :: 3.10
Classifier: Programming Language :: Python :: 3.11
Classifier: Programming Language :: Python :: 3.12
Classifier: Programming Language :: Python :: 3.13
Classifier: Topic :: Internet :: WWW/HTTP :: Dynamic Content
Requires-Dist: appium-python-client (>=5.1.0,<6.0.0)
Requires-Dist: loguru (>=0.7.0,<0.8.0)
Project-URL: Repository, https://github.com/SeldomQA/poium
